zyt_auto_tools/__init__.py
zyt_auto_tools/auto_compare.py
zyt_auto_tools/auto_create_structure.py
zyt_auto_tools/auto_generate_init.py
zyt_auto_tools/auto_init_python_dir.py
zyt_auto_tools/auto_init_python_file.py
zyt_auto_tools/auto_update_ctime.py
zyt_auto_tools/templates/__init__.py
zyt_auto_tools/templates/crawler/__init__.py
zyt_auto_tools/templates/crawler/__init__.py.txt
zyt_auto_tools/templates/crawler/config.py.txt
zyt_auto_tools/templates/crawler/logger.py.txt
zyt_auto_tools/templates/crawler/start_crawler.py.txt
zyt_auto_tools/templates/crawler/plugins/__init__.py
zyt_auto_tools/templates/crawler/plugins/__init__.py.txt
zyt_auto_tools/templates/crawler/plugins/open_chrome.py.txt
zyt_auto_tools/templates/crawler/plugins/proxy_test.py.txt
zyt_auto_tools/templates/crawler/settings/__init__.py
zyt_auto_tools/templates/crawler/settings/basic_setting.toml.txt
zyt_auto_tools/templates/crawler/settings/chrome_setting.toml.txt
zyt_auto_tools/templates/crawler/settings/cookies/__init__.py
zyt_auto_tools/templates/crawler/settings/cookies/load_cookies.toml.txt
zyt_auto_tools/templates/crawler/settings/lake/__init__.py
zyt_auto_tools/templates/crawler/settings/lake/proxies.txt.txt
zyt_auto_tools/templates/crawler/settings/lake/user_agents.txt.txt
zyt_auto_tools/templates/crawler/spiders/__init__.py
zyt_auto_tools/templates/crawler/spiders/__init__.py.txt
zyt_auto_tools/templates/crawler/spiders/example.py.txt
zyt_auto_tools/templates/crawler/utils/__init__.py
zyt_auto_tools/templates/crawler/utils/__init__.py.txt
zyt_auto_tools/templates/crawler/utils/generic_utils.py.txt
zyt_auto_tools/templates/crawler/utils/log_utils.py.txt
zyt_auto_tools/templates/init/__init__.py
zyt_auto_tools/templates/init/__init__.py.txt
zyt_auto_tools/templates/software/__init__.py
zyt_auto_tools/templates/software/__init__.py.txt
zyt_auto_tools/templates/software/config.py.txt
zyt_auto_tools/templates/software/main.py.txt
zyt_auto_tools/templates/software/utils.py.txt
zyt_auto_tools-0.5.0.dist-info/LICENSE
zyt_auto_tools-0.5.0.dist-info/METADATA
zyt_auto_tools-0.5.0.dist-info/WHEEL
zyt_auto_tools-0.5.0.dist-info/entry_points.txt
zyt_auto_tools-0.5.0.dist-info/top_level.txt
zyt_auto_tools-0.5.0.dist-info/RECORD
