Metadata-Version: 2.1
Name: zyt-auto-tools
Version: 0.5.0
Summary: A collection of automation tools for Python projects
Home-page: https://github.com/VerySeriousMan/zyt_auto_tools
Author: ZhangYuetao
Author-email: zhang894171707@gmail.com
License: UNKNOWN
Platform: UNKNOWN
Classifier: Programming Language :: Python :: 3
Classifier: License :: OSI Approved :: MIT License
Classifier: Operating System :: OS Independent
Requires-Python: >=3.6
License-File: LICENSE
